commandtax/__init__.py
commandtax/main.py
commandtax/catalogs/CommandCatalog.py
commandtax/catalogs/__init__.py
commandtax/drivers/Driver.py
commandtax/drivers/__init__.py
commandtax/drivers/builtin/Commandtax.py
commandtax/drivers/builtin/__init__.py
commandtax/flow/Connector.py
commandtax/flow/__init__.py
commandtax/models/Command.py
commandtax/models/__init__.py
commandtax-0.0.8.dist-info/LICENSE
commandtax-0.0.8.dist-info/METADATA
commandtax-0.0.8.dist-info/WHEEL
commandtax-0.0.8.dist-info/top_level.txt
commandtax-0.0.8.dist-info/RECORD
