Metadata-Version: 2.1
Name: commandtax
Version: 0.0.8
Summary: Commandtax is a driver which uses clean, one line commands to standardize and simplify working with automation, API's, and drivers.
Home-page: https://github.com/Apitax/Commandtax
Author: Shawn Clake
Author-email: shawn.clake@gmail.com
License: UNKNOWN
Keywords: restful,api,commandtax,scriptax,apitax,drivers,plugins
Platform: UNKNOWN
Classifier: Programming Language :: Python :: 3
Classifier: Operating System :: OS Independent
Requires-Dist: click
Requires-Dist: apitaxcore (==3.0.6)
